matvec-0.1.7.dist-info/WHEEL
matvec-0.1.7.dist-info/top_level.txt
matvec-0.1.7.dist-info/RECORD
matvec-0.1.7.dist-info/METADATA
matvec.libs/libstdc++-a9383cce.so.6.0.28
matvec.libs/libgomp-cd951527.so.1.0.0
matvec.libs/libgcc_s-a04fdf82.so.1
matvec/__init__.py
matvec/matvec.py
matvec/matvec/py.pyd
