Metadata-Version: 2.1
Name: matvec
Version: 0.1.7
Summary: Fast matrix transforms
Home-page: https://github.com/maniospas/matvec
Author: Emmanouil (Manios) Krasanakis
Author-email: maniospas@hotmail.com
License: UNKNOWN
Platform: UNKNOWN
Classifier: Programming Language :: Python :: 3
Classifier: License :: OSI Approved :: Apache Software License
Classifier: Operating System :: OS Independent
Requires-Dist: numpy
